cythonfragmentparser/README.MD
cythonfragmentparser/__init__.py
cythonfragmentparser/cyfragmentparser.pyx
cythonfragmentparser/cyfragmentparser_compile.py
cythonfragmentparser/requirements.txt
cythonfragmentparser/thirdparty.json
cythonfragmentparser-0.13.dist-info/LICENSE.rst
cythonfragmentparser-0.13.dist-info/METADATA
cythonfragmentparser-0.13.dist-info/WHEEL
cythonfragmentparser-0.13.dist-info/top_level.txt
cythonfragmentparser-0.13.dist-info/RECORD
