Metadata-Version: 2.1
Name: cythonfragmentparser
Version: 0.13
Summary: fragment parser for Android
Home-page: https://github.com/hansalemaos/cythonfragmentparser
Author: Johannes Fischer
Author-email: aulasparticularesdealemaosp@gmail.com
License: MIT
Keywords: Android,fragments
Classifier: Development Status :: 4 - Beta
Classifier: Programming Language :: Python :: 3 :: Only
Classifier: Programming Language :: Python :: 3.10
Classifier: Topic :: Software Development :: Libraries :: Python Modules
Classifier: Topic :: Utilities
License-File: LICENSE.rst
Requires-Dist: Cython
Requires-Dist: adbshellexecuter
Requires-Dist: flatten-any-dict-iterable-or-whatsoever
Requires-Dist: nested2nested
Requires-Dist: numpy
Requires-Dist: pandas
Requires-Dist: parifinder
Requires-Dist: setuptools
